Workbook

Sheet Start here
B2: SwapSutra - lead list
B3: Prepared 26 August 2026. Four segments, scored and prioritised, ready to work through.
B5: How to use this
B6: 1. Sort by Priority | C6: Every lead has a Fit score (1-5) that you can change. Priority updates automatically: 5 = P1 (contact now), 4 = P2 (this month), 3 or less = P3.
B7: 2. Work one segment at a time | C7: Communities convert fastest and cost nothing. Start there, then Partners, then Campus, then Creators (which usually costs money).
B8: 3. Fill the yellow cells | C8: Status, Owner and Next action date are yours to maintain. The Dashboard counts them for you.
B9: 4. Verify before contacting | C9: The Verified column says whether the handle/link was confirmed. 'Verify handle' means the organisation is real but you should search for the current handle first - student society handles change every academic year.
B11: Recommended sequence
B12: Weeks 1-2 | C12: Silent reading communities (Cubbon Reads, Pune Reads, Bandra Reads, Hyderabad Reads). Show up in person, offer a free swap corner, ask for nothing.
B13: Weeks 3-4 | C13: Bookstore and book-cafe partners in the same cities. A physical handover point is the biggest trust unlock for a swap product.
B14: Weeks 5-8 | C14: Campus ambassadors, timed to the start of a semester. Residential campuses first - handover friction is lowest there.
B15: Week 9+ | C15: Creators, once you have real swap stories and screenshots to show. Micro-creators (20k-150k) convert better per rupee than the 300k+ accounts.
B17: A note on the pitch
B18: Lead with utility | C18: Communities are wary of being marketed at. Every 'suggested first touch' in this file offers them something for free before asking for anything.
B19: Lead with money saved | C19: The Broke Bibliophiles chapters, students, and used-bookstore customers all respond to cost-per-book, not to features.
B20: Membership pricing | C20: The Indian Book Club charges Rs 99/month for a reading community with no swapping. That is useful evidence that Rs 49/month is priced to convert - and worth checking before you launch paid.
B22: Sources | C22: Compiled from Splainer's book club directory, Open Magazine's reading-communities feature, LBB Delhi, Miss Book Thief's bookstagrammer list, Meetup, Goodreads and the bookstores' own sites. Every link in the Link column was taken from a published source; see the Verified column.

Sheet Who to contact
A1: Who to actually contact
A2: Named people and published business contacts only. Nothing here is scraped personal data - every entry links to the page it came from. Where a column says 'Not published', that is the honest answer: Instagram DM is the real channel for that lead.
A4: # | B4: Organisation | C4: City | D4: Person | E4: Role | F4: Best channel | G4: Email | H4: Phone / WhatsApp | I4: Other handles | J4: How solid is this contact | K4: How to open with THIS person | L4: Source | M4: Status | N4: Contacted on
A5: 1 | B5: Champaca Bookstore, Library & Cafe | C5: Bengaluru | D5: Radhika Timbadia | E5: Founder (ecologist by training) | F5: Email | G5: hello@champaca.in | H5: +91 93536 08989 | I5: IG @champacabooks | J5: Store email published on site | K5: They already run a PAID lending library. Do not pitch swapping - pitch yourself as the software layer over the lending members they already have. | L5: https://champaca.in/pages/contact-us | M5: Not started
A6: 2 | B6: Kunzum Books | C6: Delhi NCR | D6: Ajay Jain | E6: Founder | F6: WhatsApp then email | G6: books@kunzum.com | H6: +91 92057 77295 | I6: WhatsApp +91 88002 00280 (no calls); GK-II +91 88002 00269, HKV +91 88002 00268 | J6: All published on kunzum.shop/pages/contact | K6: Ajay is a journalist-turned-bookseller who writes publicly about reviving reading culture. Lead with the culture argument, not the app. Multiple outlets = one yes gives you swap points across Delhi. | L6: https://kunzum.shop/pages/contact | M6: Not started
A7: 3 | B7: Kitab Khana | C7: Mumbai | D7: Amrita Somaiya | E7: Founder & Director | F7: Store landline then email | G7: Via kitabkhana.in contact form | H7: Fort store landline on site | I7: IG @kitabkhana | J7: Founder name verified; email not published - use the site form or call the store | K7: Runs the paid Kitab Klub (Rs 200/event). Ask to co-host one session before asking for a shelf. | L7: https://www.kitabkhana.in/en/contact-us | M7: Not started
A8: 4 | B8: Atta Galatta | C8: Bengaluru | D8: Subodh Sankar | E8: Co-founder (with Lakshmi Sankar) | F8: Phone | G8: No email published on site | H8: +91 96325 10126 / +91 80 4432 3614 | I8: IG @attagalatta | J8: Phones verified on site; no public email | K8: 2000+ events hosted and bookstore partner to Bangalore Lit Fest. He programmes constantly and needs content - offer a recurring monthly slot, not a one-off. | L8: https://www.attagalatta.com/ | M8: Not started
A9: 5 | B9: Pagdandi Bookstore & Coffee | C9: Pune | D9: Neha & Vishal Pipraiya | E9: Co-founders | F9: WhatsApp | G9: contactus@pagdandi.org | H9: +91 77559 08525 (WhatsApp) | I9: Baner, Pune | J9: Both published on pagdandi.org | K9: Husband-wife founders who quit corporate jobs for this. They respond to people who have actually visited. Go in person first if you can. | L9: https://pagdandi.org/aboutus/ | M9: Not started
A10: 6 | B10: Blossom Book House | C10: Bengaluru | D10: Mayi Gowda | E10: Owner | F10: WhatsApp / walk in | G10: No email published | H10: +91 94493 73202 (WhatsApp) | I10: IG @blossombookhouse | J10: Number published on their own site | K10: Three floors of used books on Church Street and enormous footfall. He built it from a pavement stall - practical, not corporate. Walk in, do not email. | L10: https://blossombookhouse.in/pages/about-us | M10: Not started
A11: 7 | B11: Bahrisons Booksellers - Khan Market (HQ) | C11: Delhi NCR | D11: Bahri family (Anuj Bahri) | E11: Owners | F11: Email + landline | G11: bahrisons@outlook.com | H11: 011 2469 4855 / 011 4175 7112 | I11: Saket +91 97119 63411; Gurugram +91 76786 09336; Vasant Kunj +91 95406 10800 | J11: All published on booksatbahri.com | K11: Chain with 6 NCR outlets - one agreement gives you handover points citywide. Slowest to close: start now. | L11: https://www.booksatbahri.com/content/contactus/ | M11: Not started
A12: 8 | B12: Luna Books | C12: Hyderabad | D12: Shilpa Sudhakar | E12: Founder | F12: Instagram DM | G12: Not published | H12: Not published | I12: IG - search Luna Books Hyderabad | J12: Founder verified via Scroll.in profile; contact not published | K12: She opened Luna specifically to help people discover books beyond bestsellers. Frame SwapSutra as discovery, not as cheap. | L12: https://scroll.in/article/1037700/we-want-to-help-people-to-discover-new-books-hyderabad-gets-a-new-independent-bookshop | M12: Not started
A13: 9 | B13: Akshara Books | C13: Hyderabad | D13: Store manager | E13: Owner/manager | F13: Instagram DM / walk in | G13: Not published | H13: See Justdial/LBB listing | I13: IG @aksharabookstore | J13: IG handle verified | K13: Hosts literary events already. Offer to programme one evening a month. | L13: https://www.instagram.com/aksharabookstore/ | M13: Not started
A14: 10 | B14: The White Crow Books & Coffee | C14: Mumbai | D14: Store manager | E14: Manager | F14: Instagram DM | G14: Not published | H14: Via Zomato/District listing | I14: IG @thewhitecrowbooksandcoffee | J14: IG verified; located at Jio World Drive, BKC | K14: Runs the TWC Book Club monthly. Ask to co-host, then ask for the shelf. | L14: https://www.instagram.com/thewhitecrowbooksandcoffee/ | M14: Not started
A15: 11 | B15: Cubbon Reads | C15: Bengaluru | D15: Shruti Sah & Harsh Snehanshu | E15: Founders | F15: Instagram DM + show up | G15: Not published | H15: - | I15: IG @cubbonreads | J15: Founders named in Open Magazine feature | K15: They also built Bookmark, a readers' dating app - they are product people, so they will get what you are building. Best single relationship on this whole list. Show up at Cubbon Park on a Saturday first. | L15: https://openthemagazine.com/books/book-clubs-literary-company | M15: Not started
A16: 12 | B16: Broke Bibliophiles Bangalore | C16: Bengaluru | D16: Vinay Leo | E16: Co-runs the chapter | F16: X / Instagram DM | G16: Not published | H16: - | I16: X @BibliophilesBlr | J16: Named in Open Magazine feature | K16: The name IS your pitch. Also moderates Just One More Page book club - two communities, one person. They meet at Bookworm, so this unlocks a bookstore too. | L16: https://x.com/BibliophilesBlr | M16: Not started
... A28: 24 | B28: Jaipur Literature Festival (Teamwork Arts) | C28: Pan-India | D28: Partnerships team | E28: Festival partnerships | F28: Website enquiry | G28: Via jaipurliteraturefestival.org | H28: - | I28: Now expanding to 7 cities | J28: No direct partnership email published - use the site enquiry route | K28: JLF 2027 is 14-18 Jan at Hotel Clarks Amer. Community/startup partner slots close months ahead - enquire by September. | L28: https://www.jaipurliteraturefestival.org/friend-of-the-festival | M28: Not started
B30: Green in the Email column = a real published inbox you can write to today. Amber = no public email; use the phone, WhatsApp or Instagram DM in the next columns.

Sheet Campus
A1: Campus & literary society leads
A2: Colleges and student societies for the SwapSutra Campus Ambassador programme.
A4: ID | B4: Segment | C4: Lead name | D4: City / Reach | E4: Channel | F4: Handle / Contact | G4: Link | H4: Est. audience | I4: Fit (1-5) | J4: Priority | K4: Why they fit SwapSutra | L4: Suggested first touch | M4: Verified? | N4: Status | O4: Owner | P4: Next action date | Q4: Notes
A5: CA01 | B5: Campus | C5: The Literary Society, Miranda House (DU) | D5: Delhi NCR | E5: Instagram | F5: @literarysocietymh | G5: https://www.instagram.com/literarysocietymh/ | H5: ~5-10k | I5: 5 | J5: =IF(I5="","",IF(I5>=5,"P1 - now",IF(I5=4,"P2 - this month","P3 - later"))) -> P1 - now | K5: Large, active English lit society at a DU women's college; members are heavy readers with limited budgets - exactly the swap/lend use case. | L5: DM offering a free SwapSutra campus chapter + 2 Campus Ambassador slots with membership waived for the society's core team. | M5: Verified | N5: Not started | Q5: DU north campus cluster - pair with Hindu, LSR, SRCC outreach.
A6: CA02 | B6: Campus | C6: The English Literary Society, St. Stephen's College | D6: Delhi NCR | E6: Website / email | F6: Via college dept. contact page | G6: https://www.ststephens.edu/english-lit-soc/ | H6: ~2-5k | I6: 5 | J6: =IF(I6="","",IF(I6>=5,"P1 - now",IF(I6=4,"P2 - this month","P3 - later"))) -> P1 - now | K6: One of India's oldest college lit societies; high-signal endorsement that other DU societies follow. | L6: Formal email to the society convenor proposing a semester book-swap drive + a SwapSutra-sponsored reading circle. | M6: Verified | N6: Not started
A7: CA03 | B7: Campus | C7: The Literary Club, IIT Delhi | D7: Delhi NCR | E7: Instagram | F7: @litclub.iitd | G7: https://www.instagram.com/litclub.iitd/ | H7: ~5k | I7: 4 | J7: =IF(I7="","",IF(I7>=5,"P1 - now",IF(I7=4,"P2 - this month","P3 - later"))) -> P2 - this month | K7: Hostel-based student body with dense physical proximity - ideal for in-person handovers and proof-based swaps. | L7: Pitch a hostel-wide 'swap your semester books' week; offer the club a co-branded event page. | M7: Verified | N7: Not started | Q7: Same play repeats at IIT Bombay, IIT Madras, BITS.
A8: CA04 | B8: Campus | C8: Lady Shri Ram College (LSR) - literary & debating societies | D8: Delhi NCR | E8: Instagram | F8: Search: LSR lit soc handle | G8: https://lsr.edu.in/ | H8: ~5k | I8: 4 | J8: =IF(I8="","",IF(I8>=5,"P1 - now",IF(I8=4,"P2 - this month","P3 - later"))) -> P2 - this month | K8: Strong humanities cohort, high engagement with reading culture and community events. | L8: Email the Students' Union + DM the society; lead with the Campus Ambassador programme. | M8: Verify handle | N8: Not started | Q8: Handle changes each academic year - verify before outreach.
A9: CA05 | B9: Campus | C9: Hindu College / Hansraj / Kirori Mal literary societies | D9: Delhi NCR | E9: Instagram | F9: Search per college | G9: https://www.du.ac.in/ | H9: ~10k combined | I9: 4 | J9: =IF(I9="","",IF(I9>=5,"P1 - now",IF(I9=4,"P2 - this month","P3 - later"))) -> P2 - this month | K9: Three high-footfall DU colleges within walking distance - one ambassador can service all three. | L9: Cluster pitch: one ambassador, three campuses, shared swap point. | M9: Verify handle | N9: Not started
A10: CA06 | B10: Campus | C10: St. Xavier's College, Mumbai - literary society | D10: Mumbai | E10: Instagram | F10: Search: Xaviers lit soc | G10: https://xaviers.edu.in/ | H10: ~5k | I10: 5 | J10: =IF(I10="","",IF(I10>=5,"P1 - now",IF(I10=4,"P2 - this month","P3 - later"))) -> P1 - now | K10: Anchor Mumbai campus with an established fest and literary culture; feeds the South Mumbai bookstore corridor. | L10: Approach during fest planning season with a sponsorship-in-kind offer (book swap stall). | M10: Verify handle | N10: Not started | Q10: Pair with Kitab Khana / Trilogy partnership for a joint event.
A11: CA07 | B11: Campus | C11: Sophia / Jai Hind / KC College literary clubs | D11: Mumbai | E11: Instagram | F11: Search per college | H11: ~8k combined | I11: 4 | J11: =IF(I11="","",IF(I11>=5,"P1 - now",IF(I11=4,"P2 - this month","P3 - later"))) -> P2 - this month | K11: Churchgate-Marine Lines cluster; students already commute past indie bookstores. | L11: Single ambassador covering the Churchgate cluster. | M11: Verify handle | N11: Not started
A12: CA08 | B12: Campus | C12: Fergusson College & Symbiosis, Pune | D12: Pune | E12: Instagram | F12: Search per college | H12: ~10k combined | I12: 5 | J12: =IF(I12="","",IF(I12>=5,"P1 - now",IF(I12=4,"P2 - this month","P3 - later"))) -> P1 - now | K12: Pune is India's densest student city and already has a proven public reading culture (Pune Reads). | L12: Co-host a campus edition of a Pune Reads style silent reading + swap session. | M12: Verify handle | N12: Not started | Q12: Highest ambassador-conversion potential of any city.
A13: CA09 | B13: Campus | C13: Christ University & Mount Carmel, Bengaluru | D13: Bengaluru | E13: Instagram | F13: Search per college | H13: ~15k combined | I13: 5 | J13: =IF(I13="","",IF(I13>=5,"P1 - now",IF(I13=4,"P2 - this month","P3 - later"))) -> P1 - now | K13: Very large student bodies, strong club culture, and a city with the most active reading communities in India. | L13: Pitch a Cubbon Reads x campus crossover; ambassadors run the campus swap shelf. | M13: Verify handle | N13: Not started
A14: CA10 | B14: Campus | C14: St. Joseph's University & NLSIU, Bengaluru | D14: Bengaluru | E14: Instagram | F14: Search per college | H14: ~6k combined | I14: 4 | J14: =IF(I14="","",IF(I14>=5,"P1 - now",IF(I14=4,"P2 - this month","P3 - later"))) -> P2 - this month | K14: Law and humanities students buy expensive textbooks - lending and renting are immediate value props. | L14: Lead with textbook lending/renting rather than leisure reading. | M14: Verify handle | N14: Not started | Q14: Textbook angle is the strongest paid-conversion argument.
A15: CA11 | B15: Campus | C15: Osmania University & University of Hyderabad lit clubs | D15: Hyderabad | E15: Instagram | F15: Search per college | H15: ~8k combined | I15: 4 | J15: =IF(I15="","",IF(I15>=5,"P1 - now",IF(I15=4,"P2 - this month","P3 - later"))) -> P2 - this month | K15: Large residential campuses; Hyderabad Reads already proves local demand. | L15: Approach via Hyderabad Reads for a warm intro to student organisers. | M15: Verify handle | N15: Not started
A16: CA12 | B16: Campus | C16: IIT Bombay / IIT Madras / BITS Pilani literary clubs | D16: Pan-India | E16: Instagram | F16: Search per campus | H16: ~20k combined | I16: 4 | J16: =IF(I16="","",IF(I16>=5,"P1 - now",IF(I16=4,"P2 - this month","P3 - later"))) -> P2 - this month | K16: Fully residential campuses = zero-friction physical handover, the hardest part of any swap product. | L16: Offer a campus-only swap pilot with proof-of-handover built in; measure and publish the results. | M16: Verify handle | N16: Not started | Q16: Best place to prove the handover flow works before scaling.
A18: Blue cells = your inputs (change the Fit score and it re-prioritises). Yellow cells = fill in as you work the list. Priority is a formula - do not overwrite.

Sheet Creators
A1: Bookstagram, BookTube & newsletter creators
A2: Reader-audience creators for paid, barter or partnership collaborations.
A4: ID | B4: Segment | C4: Lead name | D4: City / Reach | E4: Channel | F4: Handle / Contact | G4: Link | H4: Est. audience | I4: Fit (1-5) | J4: Priority | K4: Why they fit SwapSutra | L4: Suggested first touch | M4: Verified? | N4: Status | O4: Owner | P4: Next action date | Q4: Notes
A5: CR01 | B5: Creator | C5: Suruchi Garg - Bookly Reads | D5: Pan-India | E5: Instagram | F5: @booklyreads | G5: https://www.instagram.com/booklyreads/ | H5: 400k+ | I5: 4 | J5: =IF(I5="","",IF(I5>=5,"P1 - now",IF(I5=4,"P2 - this month","P3 - later"))) -> P2 - this month | K5: Largest Indian bookstagram audience; non-fiction and self-help readers who buy heavily and accumulate shelves. | L5: Paid collab: 'what my shelf looks like after a year of swapping' reel + a promo code. | M5: Verified | N5: Not started | Q5: Top-of-funnel reach play; expect a real rate card.
A6: CR02 | B6: Creator | C6: Nona Uppal | D6: Pan-India | E6: Instagram | F6: @nonauppal | G6: https://www.instagram.com/nonauppal/ | H6: ~399k | I6: 5 | J6: =IF(I6="","",IF(I6>=5,"P1 - now",IF(I6=4,"P2 - this month","P3 - later"))) -> P1 - now | K6: Author-creator with a young, female, fiction-reading audience - the exact SwapSutra core persona. | L6: Offer a SwapSutra reading circle hosted by her; she brings the audience, you host the space. | M6: Verified | N6: Not started | Q6: Highest audience-fit of the large accounts.
A7: CR03 | B7: Creator | C7: Gaurika Gandhi | D7: Pan-India | E7: Instagram | F7: @gaurikagandhi | G7: https://www.instagram.com/gaurikagandhi/ | H7: ~139k | I7: 4 | J7: =IF(I7="","",IF(I7>=5,"P1 - now",IF(I7=4,"P2 - this month","P3 - later"))) -> P2 - this month | K7: Mid-tier bookstagrammer with high comment engagement on recommendation posts. | L7: Barter: free lifetime membership + a featured shelf on SwapSutra in exchange for 2 posts. | M7: Verified | N7: Not started | Q7: Barter-friendly tier - good ROI.
A8: CR04 | B8: Creator | C8: Avinash Priya - Avinash Shelf | D8: Pan-India | E8: Instagram | F8: @avinashshelf | G8: https://www.instagram.com/avinashshelf/ | H8: 150k+ | I8: 3 | J8: =IF(I8="","",IF(I8>=5,"P1 - now",IF(I8=4,"P2 - this month","P3 - later"))) -> P3 - later | K8: Non-fiction/leadership audience; good for the 'buy less, borrow more' cost-saving message. | L8: Sponsored post framed on saving money on non-fiction you read once. | M8: Verified | N8: Not started
A9: CR05 | B9: Creator | C9: Vansh - Books with Vansh | D9: Pan-India | E9: Instagram | F9: @bookswithvansh | G9: https://www.instagram.com/bookswithvansh/ | H9: 90k+ | I9: 4 | J9: =IF(I9="","",IF(I9>=5,"P1 - now",IF(I9=4,"P2 - this month","P3 - later"))) -> P2 - this month | K9: Short summary format converts well to app installs; younger skewing audience. | L9: Reel series: 'I read 5 books this month and paid for none of them'. | M9: Verified | N9: Not started
A10: CR06 | B10: Creator | C10: Dr Ira Gupta - A Reader's Corner | D10: Pan-India | E10: Instagram | F10: @a.readers.corner | G10: https://www.instagram.com/a.readers.corner/ | H10: ~40k | I10: 4 | J10: =IF(I10="","",IF(I10>=5,"P1 - now",IF(I10=4,"P2 - this month","P3 - later"))) -> P2 - this month | K10: Community-first micro-creator; the size where a genuine partnership beats a paid post. | L10: Invite as a founding SwapSutra reading circle host. | M10: Verified | N10: Not started | Q10: Micro-tier: best conversion per rupee.
A11: CR07 | B11: Creator | C11: Asha Seth - Miss Book Thief | D11: Pan-India | E11: Instagram + blog | F11: @missbookthief_ | G11: https://missbookthief.com/ | H11: ~23k + blog | I11: 4 | J11: =IF(I11="","",IF(I11>=5,"P1 - now",IF(I11=4,"P2 - this month","P3 - later"))) -> P2 - this month | K11: Runs a book blog and author interviews - can give SwapSutra a long-form written feature, not just a story. | L11: Offer a founder interview / product review for the blog. | M11: Verified | N11: Not started | Q11: SEO value from the blog backlink.
A12: CR08 | B12: Creator | C12: Resh Susan - The Book Satchel | D12: Pan-India | E12: Blog + Instagram | F12: @thebooksatchel | G12: https://www.thebooksatchel.com/ | H12: Niche literary | I12: 3 | J12: =IF(I12="","",IF(I12>=5,"P1 - now",IF(I12=4,"P2 - this month","P3 - later"))) -> P3 - later | K12: Respected literary blogger; credibility with serious readers who care about translated and literary fiction. | L12: Pitch a guest essay on the economics of book ownership in India. | M12: Verified | N12: Not started
A13: CR09 | B13: Creator | C13: Sweta Samota | D13: Pan-India | E13: Instagram | F13: @swetasamota | G13: https://www.instagram.com/swetasamota/ | H13: 100k+ | I13: 3 | J13: =IF(I13="","",IF(I13>=5,"P1 - now",IF(I13=4,"P2 - this month","P3 - later"))) -> P3 - later | K13: Audience of authors and aspiring authors - a supply-side channel (authors seeding their own books). | L13: Pitch SwapSutra as a discovery channel for indie authors' books. | M13: Verified | N13: Not started | Q13: Supply-side, not demand-side.
A14: CR10 | B14: Creator | C14: Ankit Rastogi - Good Vibes with Ankit | D14: Pan-India | E14: Instagram | F14: @goodvibeswithankit | G14: https://www.instagram.com/goodvibeswithankit/ | H14: 300k+ | I14: 3 | J14: =IF(I14="","",IF(I14>=5,"P1 - now",IF(I14=4,"P2 - this month","P3 - later"))) -> P3 - later | K14: Very large reach but self-help/productivity skew - broader than the core reader persona. | L14: Only if budget allows a reach campaign; otherwise deprioritise. | M14: Verified | N14: Not started | Q14: Reach over fit.
A15: CR11 | B15: Creator | C15: Indian Booktuber (YouTube) | D15: Pan-India | E15: YouTube | F15: youtube.com/c/indianbooktuber | G15: https://www.youtube.com/c/indianbooktuber | H15: BookTube | I15: 3 | J15: =IF(I15="","",IF(I15>=5,"P1 - now",IF(I15=4,"P2 - this month","P3 - later"))) -> P3 - later | K15: Long-form video lets you actually demo the swap flow, which a static post cannot. | L15: Offer a sponsored walkthrough segment + affiliate code. | M15: Verified | N15: Not started
A16: CR12 | B16: Creator | C16: The Indian Book Club (Substack + community) | D16: Pan-India | E16: Substack | F16: indianbookclub.substack.com | G16: https://indianbookclub.substack.com/ | H16: Newsletter | I16: 4 | J16: =IF(I16="","",IF(I16>=5,"P1 - now",IF(I16=4,"P2 - this month","P3 - later"))) -> P2 - this month | K16: Paid newsletter audience already pays for reading community - proven willingness to pay ~Rs 99/month. | L16: Cross-promo: their subscribers get 2 months of SwapSutra free. | M16: Verified | N16: Not started | Q16: Closest existing paid-community precedent to your Rs 49/month model.
A18: Blue cells = your inputs (change the Fit score and it re-prioritises). Yellow cells = fill in as you work the list. Priority is a formula - do not overwrite.

Sheet Communities
A1: Reader community leads
A2: Reading communities, silent reading circles, book clubs and meetup groups.
A4: ID | B4: Segment | C4: Lead name | D4: City / Reach | E4: Channel | F4: Handle / Contact | G4: Link | H4: Est. audience | I4: Fit (1-5) | J4: Priority | K4: Why they fit SwapSutra | L4: Suggested first touch | M4: Verified? | N4: Status | O4: Owner | P4: Next action date | Q4: Notes
A5: CM01 | B5: Community | C5: Cubbon Reads | D5: Bengaluru | E5: Instagram | F5: @cubbonreads | G5: https://www.instagram.com/cubbonreads/ | H5: Very large, weekly | I5: 5 | J5: =IF(I5="","",IF(I5>=5,"P1 - now",IF(I5=4,"P2 - this month","P3 - later"))) -> P1 - now | K5: India's flagship silent reading community - hundreds gather every Saturday at Cubbon Park. Physical density is exactly what a swap network needs to bootstrap. | L5: Offer to run a free book-swap corner at a Saturday session; no branding push, just utility. | M5: Verified | N5: Not started | Q5: Founders also built a readers' dating app - open to reader products.
A6: CM02 | B6: Community | C6: Cubbon Book Club | D6: Bengaluru | E6: Instagram / X | F6: @cubbonbookclub | G6: https://www.instagram.com/cubbonbookclub/ | H6: Monthly, large | I6: 5 | J6: =IF(I6="","",IF(I6>=5,"P1 - now",IF(I6=4,"P2 - this month","P3 - later"))) -> P1 - now | K6: Structured monthly discussion groups - maps one-to-one onto SwapSutra reading circles. | L6: Offer SwapSutra as the free RSVP + reading-circle tool for their meetups. | M6: Verified | N6: Not started | Q6: Tooling angle, not an ad angle.
A7: CM03 | B7: Community | C7: Pune Reads | D7: Pune | E7: Instagram | F7: @pune.reads | G7: https://www.instagram.com/pune.reads/ | H7: Weekly, large | I7: 5 | J7: =IF(I7="","",IF(I7>=5,"P1 - now",IF(I7=4,"P2 - this month","P3 - later"))) -> P1 - now | K7: Pune's park reading movement with national press coverage; young, student-heavy, high swap intent. | L7: Joint 'bring a book, leave a book' edition; SwapSutra handles the listing and matching. | M7: Verified | N7: Not started | Q7: Pairs directly with the Pune campus leads.
A8: CM04 | B8: Community | C8: Hyderabad Reads | D8: Hyderabad | E8: Instagram | F8: @hyderabadreads | G8: https://www.instagram.com/hyderabadreads/ | H8: Weekly | I8: 5 | J8: =IF(I8="","",IF(I8>=5,"P1 - now",IF(I8=4,"P2 - this month","P3 - later"))) -> P1 - now | K8: Established silent reading community and the natural beachhead for the Hyderabad market. | L8: Same swap-corner offer as Cubbon Reads; ask for an intro to campus organisers. | M8: Verified | N8: Not started
A9: CM05 | B9: Community | C9: Bandra Reads | D9: Mumbai | E9: Instagram | F9: @bandrareads | G9: https://www.instagram.com/bandrareads/ | H9: Weekly, Joggers Park | I9: 5 | J9: =IF(I9="","",IF(I9>=5,"P1 - now",IF(I9=4,"P2 - this month","P3 - later"))) -> P1 - now | K9: Mumbai's most consistent public reading gathering; affluent, high-intent readers. | L9: Sponsor tea for a Sunday session in exchange for a swap table. | M9: Verified | N9: Not started
A10: CM06 | B10: Community | C10: Powai Reads | D10: Mumbai | E10: Instagram | F10: Search: Powai Reads | H10: Weekly | I10: 4 | J10: =IF(I10="","",IF(I10>=5,"P1 - now",IF(I10=4,"P2 - this month","P3 - later"))) -> P2 - this month | K10: North Mumbai counterpart to Bandra Reads; IIT Bombay is adjacent, so campus + community overlap. | L10: Approach jointly with the IIT Bombay lit club pitch. | M10: Verify handle | N10: Not started | Q10: Founder: Ananya Bhardwaj.
A11: CM07 | B11: Community | C11: Broke Bibliophiles - Bombay Chapter | D11: Mumbai | E11: Instagram / Goodreads | F11: @brokebombay | G11: https://www.instagram.com/brokebombay/ | H11: Established community | I11: 5 | J11: =IF(I11="","",IF(I11>=5,"P1 - now",IF(I11=4,"P2 - this month","P3 - later"))) -> P1 - now | K11: The name says it: a community built around reading affordably. Swapping and lending is their whole premise. | L11: Lead with cost-per-book savings; offer the chapter free memberships for organisers. | M11: Verified | N11: Not started | Q11: Highest message-market fit of any community lead.
A12: CM08 | B12: Community | C12: Broke Bibliophiles Bangalore | D12: Bengaluru | E12: X / Instagram | F12: @BibliophilesBlr | G12: https://x.com/BibliophilesBlr | H12: Monthly at Bookworm | I12: 5 | J12: =IF(I12="","",IF(I12>=5,"P1 - now",IF(I12=4,"P2 - this month","P3 - later"))) -> P1 - now | K12: Same affordability premise; already meets at a second-hand bookstore (Bookworm). | L12: Three-way partnership: SwapSutra + BBB + Bookworm as a physical swap point. | M12: Verified | N12: Not started | Q12: Bundles a community and a B2B lead.
A13: CM09 | B13: Community | C13: Kitaab (Delhi) | D13: Delhi NCR | E13: Instagram / NGO | F13: Search: Kitaab Delhi | H13: Since 2013 | I13: 4 | J13: =IF(I13="","",IF(I13>=5,"P1 - now",IF(I13=4,"P2 - this month","P3 - later"))) -> P2 - this month | K13: Long-running Delhi reading initiative with an NGO arm - a credibility and CSR partnership, not just reach. | L13: Propose a book-donation drive routed through SwapSutra listings. | M13: Verify handle | N13: Not started | Q13: Founders: Sneha and Navya Misran.
A14: CM10 | B14: Community | C14: Babelfish Book Club | D14: Delhi NCR | E14: X / Twitter | F14: @Babelfish_reads | G14: https://x.com/Babelfish_reads | H14: Niche, translated fiction | I14: 4 | J14: =IF(I14="","",IF(I14>=5,"P1 - now",IF(I14=4,"P2 - this month","P3 - later"))) -> P2 - this month | K14: Translated-fiction niche; already partners with a bookstore for member discounts, so partnership-friendly. | L14: Offer a SwapSutra members' discount tie-in mirroring their existing bookstore deal. | M14: Verified | N14: Not started
A15: CM11 | B15: Community | C15: Delhi Book Lovers (Meetup) | D15: Delhi NCR | E15: Meetup | F15: meetup.com/dbl-join | G15: https://www.meetup.com/dbl-join/ | H15: Meetup group | I15: 4 | J15: =IF(I15="","",IF(I15>=5,"P1 - now",IF(I15=4,"P2 - this month","P3 - later"))) -> P2 - this month | K15: Meetup groups have opt-in email lists and event RSVPs - easy, permissioned distribution. | L15: Post a free SwapSutra swap meetup on their calendar. | M15: Verified | N15: Not started
A16: CM12 | B16: Community | C16: Mumbai Book Club (Meetup) | D16: Mumbai | E16: Meetup | F16: meetup.com/book-reading-club | G16: https://www.meetup.com/book-reading-club/ | H16: Meetup group | I16: 4 | J16: =IF(I16="","",IF(I16>=5,"P1 - now",IF(I16=4,"P2 - this month","P3 - later"))) -> P2 - this month | K16: Same permissioned-distribution logic in Mumbai. | L16: Host a SwapSutra-sponsored session. | M16: Verified | N16: Not started
A17: CM13 | B17: Community | C17: Bangalore Book Reading & Tea Club (Meetup) | D17: Bengaluru | E17: Meetup | F17: meetup.com/bangalore-book-reading-tea-club | G17: https://www.meetup.com/bangalore-book-reading-tea-club/ | H17: Meetup group | I17: 4 | J17: =IF(I17="","",IF(I17>=5,"P1 - now",IF(I17=4,"P2 - this month","P3 - later"))) -> P2 - this month | K17: Recurring, tea-and-books format that maps neatly to SwapSutra meetups. | L17: Offer to co-host and cover the venue. | M17: Verified | N17: Not started
A18: CM14 | B18: Community | C18: Karuna's Kitaab Club | D18: Online | E18: Instagram | F18: @karunaskitaabclub | G18: https://www.instagram.com/karunaskitaabclub/ | H18: Virtual club | I18: 4 | J18: =IF(I18="","",IF(I18>=5,"P1 - now",IF(I18=4,"P2 - this month","P3 - later"))) -> P2 - this month | K18: Runs monthly picks and author conversations online - a direct fit for SwapSutra online meetups. | L18: Offer SwapSutra as the hosting platform for their author sessions. | M18: Verified | N18: Not started
A19: CM15 | B19: Community | C19: The Indian Book Club (@indiareadwithus) | D19: Online | E19: Instagram | F19: @indiareadwithus | G19: https://www.instagram.com/indiareadwithus/ | H19: Paid, Rs 99/mo | I19: 5 | J19: =IF(I19="","",IF(I19>=5,"P1 - now",IF(I19=4,"P2 - this month","P3 - later"))) -> P1 - now | K19: Already charges Rs 99/month for a reading community - proves your Rs 49/month membership is priced to convert. | L19: Partnership or, at minimum, pricing research. Offer a bundled cross-membership. | M19: Verified | N19: Not started | Q19: Also a competitor - read their positioning before pitching.
A20: CM16 | B20: Community | C20: PaperBackTalks | D20: Multi-city | E20: Instagram | F20: Search: PaperBackTalks | H20: Multi-city chapters | I20: 4 | J20: =IF(I20="","",IF(I20>=5,"P1 - now",IF(I20=4,"P2 - this month","P3 - later"))) -> P2 - this month | K20: Runs open mics and author interactions across several cities - one relationship, many cities. | L20: Propose SwapSutra as event partner across all chapters. | M20: Verify handle | N20: Not started | Q20: Founder: Rahul Saini.
A21: CM17 | B21: Community | C21: Bring Your Own Book (BYOB) | D21: Multi-city | E21: Newsletter | F21: Search: BYOB book club India | H21: Delhi, Mumbai, Bengaluru | I21: 4 | J21: =IF(I21="","",IF(I21>=5,"P1 - now",IF(I21=4,"P2 - this month","P3 - later"))) -> P2 - this month | K21: The 'bring your own book' format is one step away from 'swap your own book'. | L21: Pitch a swap add-on to their existing format. | M21: Verify handle | N21: Not started
A22: CM18 | B22: Community | C22: Silent Book Club - India chapters | D22: Multi-city | E22: Website | F22: silentbook.club | G22: https://silentbook.club/ | H22: Global network, Indian chapters | I22: 4 | J22: =IF(I22="","",IF(I22>=5,"P1 - now",IF(I22=4,"P2 - this month","P3 - later"))) -> P2 - this month | K22: Chapter directory gives you a ready-made list of local organisers in multiple Indian cities. | L22: Work the chapter directory city by city; offer each organiser a free swap corner kit. | M22: Verified | N22: Not started | Q22: Use as a lead source, not a single lead.
A23: CM19 | B23: Community | C23: Goodreads India / Delhi / book-exchange groups | D23: Online | E23: Goodreads | F23: goodreads.com/group/show_tag/book-exchange | G23: https://www.goodreads.com/group/show_tag/book-exchange | H23: Multiple groups | I23: 3 | J23: =IF(I23="","",IF(I23>=5,"P1 - now",IF(I23=4,"P2 - this month","P3 - later"))) -> P3 - later | K23: Explicit book-exchange intent, though Goodreads groups are lower-activity than Instagram now. | L23: Join, contribute genuinely, then mention SwapSutra where relevant. No cold spam. | M23: Verified | N23: Not started | Q23: Low effort, low-moderate yield.
A25: Blue cells = your inputs (change the Fit score and it re-prioritises). Yellow cells = fill in as you work the list. Priority is a formula - do not overwrite.

Sheet Partners
A1: Partner organisation leads (B2B)
A2: Bookstores, book cafes, co-working spaces, publishers and festivals.
A4: ID | B4: Segment | C4: Lead name | D4: City / Reach | E4: Channel | F4: Handle / Contact | G4: Link | H4: Est. audience | I4: Fit (1-5) | J4: Priority | K4: Why they fit SwapSutra | L4: Suggested first touch | M4: Verified? | N4: Status | O4: Owner | P4: Next action date | Q4: Notes
A5: PT01 | B5: Partner | C5: Kitab Khana / Kitab Klub | D5: Mumbai | E5: Instagram / in-store | F5: @kitabkhana | G5: https://www.instagram.com/kitabkhana/ | H5: Fort, Mumbai | I5: 5 | J5: =IF(I5="","",IF(I5>=5,"P1 - now",IF(I5=4,"P2 - this month","P3 - later"))) -> P1 - now | K5: Landmark Mumbai bookstore already running a paid monthly book club - infrastructure and audience in one. | L5: Propose a SwapSutra swap shelf in-store; they get footfall, you get a verified handover point. | M5: Verified | N5: Not started | Q5: Physical handover points are the single biggest trust unlock.
A6: PT02 | B6: Partner | C6: White Crow Books & Coffee (TWC Book Club) | D6: Mumbai | E6: Instagram | F6: @thewhitecrowbooksandcoffee | G6: https://www.instagram.com/thewhitecrowbooksandcoffee/ | H6: Cafe + club | I6: 5 | J6: =IF(I6="","",IF(I6>=5,"P1 - now",IF(I6=4,"P2 - this month","P3 - later"))) -> P1 - now | K6: Bookstore-cafe that already hosts a monthly club - venue, audience and reason-to-visit all present. | L6: Co-host a SwapSutra meetup; offer members a discount at the cafe. | M6: Verified | N6: Not started
A7: PT03 | B7: Partner | C7: Champaca Bookstore, Library & Cafe | D7: Bengaluru | E7: Website / Instagram | F7: champaca.in | G7: https://champaca.in/ | H7: Vasanth Nagar | I7: 5 | J7: =IF(I7="","",IF(I7>=5,"P1 - now",IF(I7=4,"P2 - this month","P3 - later"))) -> P1 - now | K7: Runs a paid lending library already - they understand and have validated the borrow-not-buy model. | L7: Pitch a partnership rather than a promo: SwapSutra as the digital layer over their lending members. | M7: Verified | N7: Not started | Q7: Closest philosophical fit of any partner.
A8: PT04 | B8: Partner | C8: Bookworm Bangalore | D8: Bengaluru | E8: In-store | F8: Search: Bookworm Church Street | H8: Church Street | I8: 5 | J8: =IF(I8="","",IF(I8>=5,"P1 - now",IF(I8=4,"P2 - this month","P3 - later"))) -> P1 - now | K8: Bengaluru's best-known second-hand bookstore and the meeting venue for Broke Bibliophiles Bangalore. | L8: Warm intro via Broke Bibliophiles; propose a swap point and a listings tie-in. | M8: Verify contact | N8: Not started | Q8: Second-hand stores are natural allies, not competitors.
A9: PT05 | B9: Partner | C9: Select Bookshop | D9: Bengaluru | E9: In-store | F9: Brigade Road | H9: 80-year institution | I9: 4 | J9: =IF(I9="","",IF(I9>=5,"P1 - now",IF(I9=4,"P2 - this month","P3 - later"))) -> P2 - this month | K9: Sources pre-loved and vintage titles - shared 'books should circulate' philosophy. | L9: In-person visit; propose a curated pre-loved listing feed on SwapSutra. | M9: Verify contact | N9: Not started
A10: PT06 | B10: Partner | C10: Bahrisons Booksellers | D10: Delhi NCR | E10: Website / stores | F10: booksatbahri.com | G10: https://en.wikipedia.org/wiki/Bahrisons_Booksellers | H10: Multiple NCR stores | I10: 4 | J10: =IF(I10="","",IF(I10>=5,"P1 - now",IF(I10=4,"P2 - this month","P3 - later"))) -> P2 - this month | K10: Delhi's best-known chain with several NCR outlets - one deal gives you handover points across the city. | L10: Formal partnership proposal to head office, framed around footfall from SwapSutra users. | M10: Verified | N10: Not started | Q10: Slower to close; start early.
A11: PT07 | B11: Partner | C11: Faqir Chand Bookstore, Khan Market | D11: Delhi NCR | E11: In-store | F11: Khan Market | H11: Heritage, since 1948 | I11: 4 | J11: =IF(I11="","",IF(I11>=5,"P1 - now",IF(I11=4,"P2 - this month","P3 - later"))) -> P2 - this month | K11: Heritage credibility in a high-footfall market; fourth-generation owners with deep reader relationships. | L11: In-person visit with a printed one-pager - this is not an Instagram-DM audience. | M11: Verified | N11: Not started
A12: PT08 | B12: Partner | C12: Kunzum Travel Cafe (multiple NCR outlets) | D12: Delhi NCR | E12: Cafe + bookstore | F12: Search: Kunzum | H12: Several NCR locations | I12: 5 | J12: =IF(I12="","",IF(I12>=5,"P1 - now",IF(I12=4,"P2 - this month","P3 - later"))) -> P1 - now | K12: Book-cafe chain with a browse-and-linger model and multiple locations - ideal distributed swap points. | L12: Pitch all outlets at once as SwapSutra 'swap stations'. | M12: Verified | N12: Not started | Q12: Multi-location = high leverage.
A13: PT09 | B13: Partner | C13: Cafe Turtle / Full Circle Bookstore | D13: Delhi NCR | E13: Cafe + bookstore | F13: Khan Market & other outlets | H13: Established | I13: 4 | J13: =IF(I13="","",IF(I13>=5,"P1 - now",IF(I13=4,"P2 - this month","P3 - later"))) -> P2 - this month | K13: Bookstore-cafe pairing with an existing literary events calendar. | L13: Offer to fill a slow weekday evening slot with a SwapSutra reading circle. | M13: Verified | N13: Not started
A14: PT10 | B14: Partner | C14: Jugmug Thela, Saidulajab | D14: Delhi NCR | E14: Cafe | F14: Search: Jugmug Thela | H14: Reading room | I14: 4 | J14: =IF(I14="","",IF(I14>=5,"P1 - now",IF(I14=4,"P2 - this month","P3 - later"))) -> P2 - this month | K14: Already sells pre-loved books at a discount from a dedicated reading room - a swap shelf is a small ask. | L14: Small, concrete ask: one shelf, SwapSutra-branded, listings synced. | M14: Verified | N14: Not started | Q14: Easy first yes.
A15: PT11 | B15: Partner | C15: Book Talk, Dwarka | D15: Delhi NCR | E15: Library cafe | F15: Search: Book Talk Dwarka | H15: Library-meets-cafe | I15: 4 | J15: =IF(I15="","",IF(I15>=5,"P1 - now",IF(I15=4,"P2 - this month","P3 - later"))) -> P2 - this month | K15: Already runs borrowing plus events - operationally closest to what SwapSutra does offline. | L15: Offer SwapSutra as their free borrowing-management tool. | M15: Verified | N15: Not started | Q15: Product-led partnership.
A16: PT12 | B16: Partner | C16: The Nerdy Indian, Sainik Farms | D16: Delhi NCR | E16: Cafe | F16: Search: The Nerdy Indian | H16: ~1000 book library | I16: 3 | J16: =IF(I16="","",IF(I16>=5,"P1 - now",IF(I16=4,"P2 - this month","P3 - later"))) -> P3 - later | K16: Large in-house library and an audience that already borrows on site. | L16: Swap shelf + cross-promo vouchers. | M16: Verified | N16: Not started
A17: PT13 | B17: Partner | C17: Luna Books | D17: Hyderabad | E17: Bookstore | F17: Search: Luna Books Hyderabad | H17: Two-storey, curated | I17: 4 | J17: =IF(I17="","",IF(I17>=5,"P1 - now",IF(I17=4,"P2 - this month","P3 - later"))) -> P2 - this month | K17: Hyderabad's most-recommended indie store; curation-led, so their endorsement carries weight locally. | L17: Approach alongside Hyderabad Reads for a joint city launch. | M17: Verified | N17: Not started
A18: PT14 | B18: Partner | C18: Akshara Books, Jubilee Hills | D18: Hyderabad | E18: Bookstore | F18: Search: Akshara Books | H18: Hosts literary events | I18: 4 | J18: =IF(I18="","",IF(I18>=5,"P1 - now",IF(I18=4,"P2 - this month","P3 - later"))) -> P2 - this month | K18: Already hosts literary and artistic events - a venue partner for SwapSutra meetups. | L18: Offer to programme one event a month. | M18: Verified | N18: Not started
A19: PT15 | B19: Partner | C19: Pagdandi Books Chai Cafe | D19: Pune | E19: Bookstore cafe | F19: Search: Pagdandi Pune | H19: Baner, Pune | I19: 5 | J19: =IF(I19="","",IF(I19>=5,"P1 - now",IF(I19=4,"P2 - this month","P3 - later"))) -> P1 - now | K19: Pune's landmark book-cafe with a strong community programme; pairs with Pune Reads and the campus cluster. | L19: Anchor partner for a Pune city launch. | M19: Verify contact | N19: Not started | Q19: Make Pune the first full city pilot.
A20: PT16 | B20: Partner | C20: Atta Galatta | D20: Bengaluru | E20: Bookstore + events | F20: attagalatta.com | G20: https://www.attagalatta.com/ | H20: Koramangala | I20: 5 | J20: =IF(I20="","",IF(I20>=5,"P1 - now",IF(I20=4,"P2 - this month","P3 - later"))) -> P1 - now | K20: Runs one of India's busiest independent literary event calendars - immediate access to organised readers. | L20: Propose a recurring monthly SwapSutra swap-and-read evening. | M20: Verified | N20: Not started | Q20: High-volume events venue.
A21: PT17 | B21: Partner | C21: Blossom Book House | D21: Bengaluru | E21: Bookstore | F21: Church Street | H21: Very high footfall, used books | I21: 5 | J21: =IF(I21="","",IF(I21>=5,"P1 - now",IF(I21=4,"P2 - this month","P3 - later"))) -> P1 - now | K21: India's most famous used-bookstore; enormous footfall of exactly the price-sensitive reader you want. | L21: Flyer/QR partnership at the counter plus a swap point upstairs. | M21: Verified | N21: Not started | Q21: Highest raw footfall on this list.
A22: PT18 | B22: Partner | C22: Co-working spaces with libraries (WeWork, 91springboard, Bhive) | D22: Multi-city | E22: B2B partnerships | F22: Community managers | H22: Corporate readers | I22: 3 | J22: =IF(I22="","",IF(I22>=5,"P1 - now",IF(I22=4,"P2 - this month","P3 - later"))) -> P3 - later | K22: Community managers need free programming; a SwapSutra book shelf and monthly circle is easy for them to say yes to. | L22: Email community managers offering ready-made programming at no cost. | M22: Verify contact | N22: Not started | Q22: Scales fast once one location says yes.
A23: PT19 | B23: Partner | C23: Publishers - HarperCollins India, Penguin RH India, Juggernaut | D23: Pan-India | E23: Marketing teams | F23: Marketing / community leads | H23: National | I23: 3 | J23: =IF(I23="","",IF(I23>=5,"P1 - now",IF(I23=4,"P2 - this month","P3 - later"))) -> P3 - later | K23: Publishers want reader data and launch reach; SwapSutra reading circles are a distribution channel for new titles. | L23: Pitch reading-circle placements for new releases; ask for review copies as circle giveaways. | M23: Verify contact | N23: Not started | Q23: Long sales cycle - start conversations now, expect results in 6+ months.
A24: PT20 | B24: Partner | C24: Jaipur Literature Festival & city lit fests | D24: Pan-India | E24: Events | F24: Festival partnerships teams | H24: Tens of thousands | I24: 4 | J24: =IF(I24="","",IF(I24>=5,"P1 - now",IF(I24=4,"P2 - this month","P3 - later"))) -> P2 - this month | K24: Single highest concentration of Indian readers in one place; a swap booth is a natural fit. | L24: Apply for a community/startup partner slot well before the season. | M24: Verify contact | N24: Not started | Q24: Plan 4-6 months ahead of the festival calendar.
A26: Blue cells = your inputs (change the Fit score and it re-prioritises). Yellow cells = fill in as you work the list. Priority is a formula - do not overwrite.

Sheet Dashboard
B2: Pipeline dashboard
B3: Updates automatically as you fill in the Status column on each tab.
B5: Segment | C5: Leads | D5: P1 | E5: P2 | F5: P3 | G5: Not started | H5: Researching | I5: Contacted | J5: In conversation | K5: Won | L5: Passed
B6: Campus | C6: =COUNTA(Campus!$C$5:$C$16) -> 12 | D6: =COUNTIF(Campus!$I$5:$I$16,5) -> 5 | E6: =COUNTIF(Campus!$I$5:$I$16,4) -> 7 | F6: =COUNTIF(Campus!$I$5:$I$16,"<=3") -> 0 | G6: =COUNTIF(Campus!$N$5:$N$16,"Not started") -> 12 | H6: =COUNTIF(Campus!$N$5:$N$16,"Researching") -> 0 | I6: =COUNTIF(Campus!$N$5:$N$16,"Contacted") -> 0 | J6: =COUNTIF(Campus!$N$5:$N$16,"In conversation") -> 0 | K6: =COUNTIF(Campus!$N$5:$N$16,"Won") -> 0 | L6: =COUNTIF(Campus!$N$5:$N$16,"Passed") -> 0
B7: Creators | C7: =COUNTA(Creators!$C$5:$C$16) -> 12 | D7: =COUNTIF(Creators!$I$5:$I$16,5) -> 1 | E7: =COUNTIF(Creators!$I$5:$I$16,4) -> 6 | F7: =COUNTIF(Creators!$I$5:$I$16,"<=3") -> 5 | G7: =COUNTIF(Creators!$N$5:$N$16,"Not started") -> 12 | H7: =COUNTIF(Creators!$N$5:$N$16,"Researching") -> 0 | I7: =COUNTIF(Creators!$N$5:$N$16,"Contacted") -> 0 | J7: =COUNTIF(Creators!$N$5:$N$16,"In conversation") -> 0 | K7: =COUNTIF(Creators!$N$5:$N$16,"Won") -> 0 | L7: =COUNTIF(Creators!$N$5:$N$16,"Passed") -> 0
B8: Communities | C8: =COUNTA(Communities!$C$5:$C$23) -> 19 | D8: =COUNTIF(Communities!$I$5:$I$23,5) -> 8 | E8: =COUNTIF(Communities!$I$5:$I$23,4) -> 10 | F8: =COUNTIF(Communities!$I$5:$I$23,"<=3") -> 1 | G8: =COUNTIF(Communities!$N$5:$N$23,"Not started") -> 19 | H8: =COUNTIF(Communities!$N$5:$N$23,"Researching") -> 0 | I8: =COUNTIF(Communities!$N$5:$N$23,"Contacted") -> 0 | J8: =COUNTIF(Communities!$N$5:$N$23,"In conversation") -> 0 | K8: =COUNTIF(Communities!$N$5:$N$23,"Won") -> 0 | L8: =COUNTIF(Communities!$N$5:$N$23,"Passed") -> 0
B9: Partners | C9: =COUNTA(Partners!$C$5:$C$24) -> 20 | D9: =COUNTIF(Partners!$I$5:$I$24,5) -> 8 | E9: =COUNTIF(Partners!$I$5:$I$24,4) -> 9 | F9: =COUNTIF(Partners!$I$5:$I$24,"<=3") -> 3 | G9: =COUNTIF(Partners!$N$5:$N$24,"Not started") -> 20 | H9: =COUNTIF(Partners!$N$5:$N$24,"Researching") -> 0 | I9: =COUNTIF(Partners!$N$5:$N$24,"Contacted") -> 0 | J9: =COUNTIF(Partners!$N$5:$N$24,"In conversation") -> 0 | K9: =COUNTIF(Partners!$N$5:$N$24,"Won") -> 0 | L9: =COUNTIF(Partners!$N$5:$N$24,"Passed") -> 0
B10: Total | C10: =SUM(C6:C9) -> 63 | D10: =SUM(D6:D9) -> 22 | E10: =SUM(E6:E9) -> 32 | F10: =SUM(F6:F9) -> 9 | G10: =SUM(G6:G9) -> 63 | H10: =SUM(H6:H9) -> 0 | I10: =SUM(I6:I9) -> 0 | J10: =SUM(J6:J9) -> 0 | ... L10: =SUM(L6:L9) -> 0
B12: P1/P2/P3 are driven by the Fit score on each tab. Contacted-onwards counts come from the Status dropdowns.
